Workbook
Name Slicer_category: #N/A
Name Slicer_region: #N/A

Sheet Sheet1
A1: order_id | B1: Order_Month | C1: order_date | D1: region | E1: sales | F1: category | G1: discount | H1: quantity | I1: delivery_date | J1: customer_type | K1: payment_mode | L1: profit | M1: city
A2: ORD100000 | B2: =TEXT(C2,"MMMM") -> March | C2: 45015 | D2: East | E2: 713.49 | F2: Clothing | G2: =E2*10% -> 71.349 | H2: 3 | I2: 45017 | J2: Member | K2: UPI | L2: 114.72 | M2: Pune
A3: ORD100001 | B3: =TEXT(C3,"MMMM") -> August | C3: 45166 | D3: West | E3: 3802.97 | F3: Electronics | G3: =E3*10% -> 380.297 | H3: 4 | I3: 45172 | J3: Regular | K3: Card | L3: 971.41 | M3: Hyderabad
A4: ORD100002 | B4: =TEXT(C4,"MMMM") -> March | C4: 45360 | D4: North | E4: 3588.97 | F4: Home Care | G4: =E4*10% -> 358.897 | H4: 7 | I4: 45366 | J4: Regular | K4: Cash | L4: 769.08 | M4: Bangalore
A5: ORD100003 | B5: =TEXT(C5,"MMMM") -> October | C5: 45578 | D5: East | E5: 1160.86 | F5: Electronics | G5: =E5*10% -> 116.086 | H5: 5 | I5: 45584 | J5: Member | K5: UPI | L5: 71.61 | M5: Pune
A6: ORD100004 | B6: =TEXT(C6,"MMMM") -> April | C6: 45022 | D6: East | E6: 3071.32 | F6: Electronics | G6: =E6*10% -> 307.132 | H6: 7 | I6: 45025 | J6: New | K6: Cash | L6: 621.92 | M6: Bangalore
A7: ORD100005 | B7: =TEXT(C7,"MMMM") -> July | C7: 45108 | D7: West | E7: 2566.18 | F7: Grocery | G7: =E7*10% -> 256.618 | H7: 6 | I7: 45111 | J7: Member | K7: UPI | L7: 578.94 | M7: Mumbai
A8: ORD100006 | B8: =TEXT(C8,"MMMM") -> July | C8: 45119 | D8: North | E8: 398 | F8: Personal Care | G8: =E8*10% -> 39.8 | H8: 4 | I8: 45124 | J8: New | K8: Cash | L8: 110.31 | M8: Mumbai
A9: ORD100007 | B9: =TEXT(C9,"MMMM") -> May | C9: 45064 | D9: North | E9: 1462.95 | F9: Personal Care | G9: =E9*10% -> 146.295 | H9: 2 | I9: 45066 | J9: Regular | K9: UPI | L9: 91.68 | M9: Bangalore
A10: ORD100008 | B10: =TEXT(C10,"MMMM") -> January | C10: 45296 | D10: East | E10: 4997.47 | F10: Personal Care | G10: =E10*10% -> 499.747 | H10: 6 | I10: 45299 | J10: Regular | K10: Card | L10: 995.78 | M10: Delhi
A11: ORD100009 | B11: =TEXT(C11,"MMMM") -> August | C11: 45514 | D11: South | E11: 587.72 | F11: Grocery | G11: =E11*10% -> 58.772 | H11: 6 | I11: 45521 | J11: New | K11: Cash | L11: 102.96 | M11: Pune
A12: ORD100010 | B12: =TEXT(C12,"MMMM") -> May | C12: 45419 | D12: East | E12: 2581.42 | F12: Clothing | G12: =E12*10% -> 258.142 | H12: 6 | I12: 45420 | J12: Regular | K12: Cash | L12: 542.82 | M12: Bangalore
A13: ORD100011 | B13: =TEXT(C13,"MMMM") -> September | C13: 45171 | D13: East | E13: 4261.74 | F13: Clothing | G13: =E13*10% -> 426.174 | H13: 1 | I13: 45172 | J13: New | K13: UPI | L13: 1028.47 | M13: Pune
... A15346: ORD115344 | B15346: =TEXT(C15346,"MMMM") -> November | C15346: 45248 | D15346: South | E15346: 4984.32 | F15346: Grocery | G15346: =E15346*10% -> 498.432 | H15346: 3 | I15346: 45249 | J15346: New | K15346: Card | L15346: 909.1 | M15346: Bangalore

Sheet Sheet2
A1: order_id | B1: sales
A2: ORD100000 | B2: =VLOOKUP(A2,Sheet1!A1:E15346,5,0) -> 713.49
A3: ORD100001 | B3: =VLOOKUP(A3,Sheet1!A2:E15347,5,0) -> 3802.97
A4: ORD100002 | B4: =VLOOKUP(A4,Sheet1!A3:E15348,5,0) -> 3588.97
A5: ORD100003 | B5: =VLOOKUP(A5,Sheet1!A4:E15349,5,0) -> 1160.86
A6: ORD100004 | B6: =VLOOKUP(A6,Sheet1!A5:E15350,5,0) -> 3071.32
A7: ORD100005 | B7: =VLOOKUP(A7,Sheet1!A6:E15351,5,0) -> 2566.18
A8: ORD100006 | B8: =VLOOKUP(A8,Sheet1!A7:E15352,5,0) -> 398
A9: ORD100007 | B9: =VLOOKUP(A9,Sheet1!A8:E15353,5,0) -> 1462.95
A10: ORD100008 | B10: =VLOOKUP(A10,Sheet1!A9:E15354,5,0) -> 4997.47
A11: ORD100009 | B11: =VLOOKUP(A11,Sheet1!A10:E15355,5,0) -> 587.72
A12: ORD100010 | B12: =VLOOKUP(A12,Sheet1!A11:E15356,5,0) -> 2581.42
A13: ORD100011 | B13: =VLOOKUP(A13,Sheet1!A12:E15357,5,0) -> 4261.74
... A15346: ORD115344 | B15346: =VLOOKUP(A15346,Sheet1!A15345:E30690,5,0) -> 4984.32

Sheet Sheet3
A1: order_id | B1: profit
A2: ORD100000 | B2: =_xlfn.XLOOKUP(A2,Table_1[order_id],Table_1[profit]) -> 114.72
A3: ORD100001 | B3: =_xlfn.XLOOKUP(A3,Table_1[order_id],Table_1[profit]) -> 971.41
A4: ORD100002 | B4: =_xlfn.XLOOKUP(A4,Table_1[order_id],Table_1[profit]) -> 769.08
A5: ORD100003 | B5: =_xlfn.XLOOKUP(A5,Table_1[order_id],Table_1[profit]) -> 71.61
A6: ORD100004 | B6: =_xlfn.XLOOKUP(A6,Table_1[order_id],Table_1[profit]) -> 621.92
A7: ORD100005 | B7: =_xlfn.XLOOKUP(A7,Table_1[order_id],Table_1[profit]) -> 578.94
A8: ORD100006 | B8: =_xlfn.XLOOKUP(A8,Table_1[order_id],Table_1[profit]) -> 110.31
A9: ORD100007 | B9: =_xlfn.XLOOKUP(A9,Table_1[order_id],Table_1[profit]) -> 91.68
A10: ORD100008 | B10: =_xlfn.XLOOKUP(A10,Table_1[order_id],Table_1[profit]) -> 995.78
A11: ORD100009 | B11: =_xlfn.XLOOKUP(A11,Table_1[order_id],Table_1[profit]) -> 102.96
A12: ORD100010 | B12: =_xlfn.XLOOKUP(A12,Table_1[order_id],Table_1[profit]) -> 542.82
A13: ORD100011 | B13: =_xlfn.XLOOKUP(A13,Table_1[order_id],Table_1[profit]) -> 1028.47
... A15346: ORD115344 | B15346: =_xlfn.XLOOKUP(A15346,Table_1[order_id],Table_1[profit]) -> 909.1

Sheet Sheet4
A1: order_id | B1: City
A2: ORD100000 | B2: =INDEX(Sheet1!M1:M15346,MATCH(A2,Sheet4!A1:A15346,0)) -> Pune
A3: ORD100001 | B3: =INDEX(Sheet1!M2:M15347,MATCH(A3,Sheet4!A2:A15347,0)) -> Hyderabad
A4: ORD100002 | B4: =INDEX(Sheet1!M3:M15348,MATCH(A4,Sheet4!A3:A15348,0)) -> Bangalore
A5: ORD100003 | B5: =INDEX(Sheet1!M4:M15349,MATCH(A5,Sheet4!A4:A15349,0)) -> Pune
A6: ORD100004 | B6: =INDEX(Sheet1!M5:M15350,MATCH(A6,Sheet4!A5:A15350,0)) -> Bangalore
A7: ORD100005 | B7: =INDEX(Sheet1!M6:M15351,MATCH(A7,Sheet4!A6:A15351,0)) -> Mumbai
A8: ORD100006 | B8: =INDEX(Sheet1!M7:M15352,MATCH(A8,Sheet4!A7:A15352,0)) -> Mumbai
A9: ORD100007 | B9: =INDEX(Sheet1!M8:M15353,MATCH(A9,Sheet4!A8:A15353,0)) -> Bangalore
A10: ORD100008 | B10: =INDEX(Sheet1!M9:M15354,MATCH(A10,Sheet4!A9:A15354,0)) -> Delhi
A11: ORD100009 | B11: =INDEX(Sheet1!M10:M15355,MATCH(A11,Sheet4!A10:A15355,0)) -> Pune
A12: ORD100010 | B12: =INDEX(Sheet1!M11:M15356,MATCH(A12,Sheet4!A11:A15356,0)) -> Bangalore
A13: ORD100011 | B13: =INDEX(Sheet1!M12:M15357,MATCH(A13,Sheet4!A12:A15357,0)) -> Pune
... A15346: ORD115344 | B15346: =INDEX(Sheet1!M15345:M30690,MATCH(A15346,Sheet4!A15345:A30690,0)) -> Bangalore

Sheet Sheet5
